{
  "artifact_count": 106,
  "artifacts": [
    {
      "bytes": 8176,
      "format": "json",
      "path": "demo/adoption_notes.json",
      "producer_command": "adoption-notes",
      "sha256": "ffd44ddaf8d88dbc116e39f0924fdb940b7493c9268363c5954b6f88eed6059b",
      "status": "present"
    },
    {
      "bytes": 5020,
      "format": "md",
      "path": "demo/adoption_notes.md",
      "producer_command": "adoption-notes",
      "sha256": "a6a314431499edb089c60a8d5de92a8e9250eb54a78d1542fd97360651a34152",
      "status": "present"
    },
    {
      "bytes": 15029,
      "format": "html",
      "path": "demo/api_reference.html",
      "producer_command": "api-reference",
      "sha256": "774471c303c4088da3c167fe2849b3220d5e6f2ff0eb027523fbda1a0901e66d",
      "status": "present"
    },
    {
      "bytes": 47299,
      "format": "json",
      "path": "demo/api_reference.json",
      "producer_command": "api-reference",
      "sha256": "b82a42e9cbf674379c1bd05d6ab9c645f51c7adb7d79684cf1375f976eaaff7a",
      "status": "present"
    },
    {
      "bytes": 21138,
      "format": "md",
      "path": "demo/api_reference.md",
      "producer_command": "api-reference",
      "sha256": "e765a0f16dea6f5ea435fd1fbc3aa1b0b54491feea395b98255958843a763fb9",
      "status": "present"
    },
    {
      "bytes": 27463,
      "format": "json",
      "path": "demo/artifact_index.json",
      "producer_command": "artifact-index",
      "sha256": "6e767512e0bcd303497b7fa4468ff98d55ff1c20e4a9d2c583d7072509871a00",
      "status": "present"
    },
    {
      "bytes": 10075,
      "format": "md",
      "path": "demo/artifact_index.md",
      "producer_command": "artifact-index",
      "sha256": "a7e3d8ff9c7c8520bfddf1a22092d9fa623a3b3d5e53131572bf2391ef204b49",
      "status": "present"
    },
    {
      "bytes": 2500,
      "format": "json",
      "path": "demo/assumption_registry.json",
      "producer_command": "assumption-registry",
      "sha256": "24f1cb2faaf193e677811eb594b4fec0c77732094bf09d8eda7d35f0135a68b9",
      "status": "present"
    },
    {
      "bytes": 1980,
      "format": "md",
      "path": "demo/assumption_registry.md",
      "producer_command": "assumption-registry",
      "sha256": "b0f851a867a3216de53af10ebc83f6aa0a9818e6f09249ceace646cc5e8dae53",
      "status": "present"
    },
    {
      "bytes": 3043,
      "format": "json",
      "path": "demo/benchmark_suite.json",
      "producer_command": "benchmark-suite",
      "sha256": "287d3fd6ac67014fcca71276ec9a1f0ec0540b97b1a5c4a77d872c7978ce447d",
      "status": "present"
    },
    {
      "bytes": 1916,
      "format": "md",
      "path": "demo/benchmark_suite.md",
      "producer_command": "benchmark-suite",
      "sha256": "86a7f8561a279961f99225efce9c01638690a974eb72f1772ac6e499c3519b9c",
      "status": "present"
    },
    {
      "bytes": 2101,
      "format": "json",
      "path": "demo/boundary_attestation.json",
      "producer_command": "boundary-attestation",
      "sha256": "3aaf0a1cff28aa03785cd264524c816f67a7c8fde219ef33955b7f38c0eae1c1",
      "status": "present"
    },
    {
      "bytes": 1485,
      "format": "md",
      "path": "demo/boundary_attestation.md",
      "producer_command": "boundary-attestation",
      "sha256": "7d8b8c99e7410411fd73f97ebb75775d6b157428364d2417d77afccb62a5c737",
      "status": "present"
    },
    {
      "bytes": 13596,
      "format": "json",
      "path": "demo/bundle_export/manifest.json",
      "producer_command": "bundle-export",
      "sha256": "2f2cc81e743bb4c07c3c9dfcf02304cbcd4b6000663492bb2e418c06307b9a99",
      "status": "present"
    },
    {
      "bytes": 6084,
      "format": "md",
      "path": "demo/bundle_export/manifest.md",
      "producer_command": "bundle-export",
      "sha256": "00607605571998c53f43a3374627d77b5b076b6160df3311bc5952a925057f84",
      "status": "present"
    },
    {
      "bytes": 4180,
      "format": "json",
      "path": "demo/case_gallery.json",
      "producer_command": "case-gallery",
      "sha256": "526e837ce331afd0a236a41bba89d46f0065dba23d863b257a3b7da27a9056cf",
      "status": "present"
    },
    {
      "bytes": 1776,
      "format": "md",
      "path": "demo/case_gallery.md",
      "producer_command": "case-gallery",
      "sha256": "22a9ea47c93c5df5ad74d92748adb0d0621c3d7747015b82be9ba4221e10ca6e",
      "status": "present"
    },
    {
      "bytes": 5723,
      "format": "json",
      "path": "demo/citation_map.json",
      "producer_command": "citation-map",
      "sha256": "4529b3419379996f9148d78e9070c71c3edad84f98cb089ad46db5a7dc9ef618",
      "status": "present"
    },
    {
      "bytes": 2058,
      "format": "md",
      "path": "demo/citation_map.md",
      "producer_command": "citation-map",
      "sha256": "b3f097f4d5ea3a4320302e6c9cf72dad2e7d94b1c546ea810fc6fe0638ec5764",
      "status": "present"
    },
    {
      "bytes": 22174,
      "format": "json",
      "path": "demo/cli_help.json",
      "producer_command": "cli-help",
      "sha256": "49979ac371db2feb3da0299a6c82f3d7227e0ce84387045d6cddecee30236f75",
      "status": "present"
    },
    {
      "bytes": 15558,
      "format": "md",
      "path": "demo/cli_help.md",
      "producer_command": "cli-help",
      "sha256": "27377a4cfac85de10eca48a65e343a8355519fc191e1409514411a917cae2dbb",
      "status": "present"
    },
    {
      "bytes": 4825,
      "format": "json",
      "path": "demo/cold_start_walkthrough.json",
      "producer_command": "cold-start-walkthrough",
      "sha256": "7b3233c8a2ac3343327c319ab162a278e38ace5d5d2665a5fd92b554fcdfef80",
      "status": "present"
    },
    {
      "bytes": 3810,
      "format": "md",
      "path": "demo/cold_start_walkthrough.md",
      "producer_command": "cold-start-walkthrough",
      "sha256": "0d646cc4c4b95db03ed7f3c60e285c8dace8306d56431554f5205408e60afbaf",
      "status": "present"
    },
    {
      "bytes": 23315,
      "format": "json",
      "path": "demo/command_matrix.json",
      "producer_command": "command-matrix",
      "sha256": "6655681f7e4196486f62206aef6c6e1d944afdef4505321067960e1bf5153191",
      "status": "present"
    },
    {
      "bytes": 15708,
      "format": "md",
      "path": "demo/command_matrix.md",
      "producer_command": "command-matrix",
      "sha256": "f6599d5a8f001d3e5ea32ff8eee819211df367775edcc930fd579e21499414d3",
      "status": "present"
    },
    {
      "bytes": 2257,
      "format": "json",
      "path": "demo/compatibility_report.json",
      "producer_command": "compatibility-report",
      "sha256": "0a222de323e14ab63b488e4603f6225330505cc7597f716f422acdf45ce4e65d",
      "status": "present"
    },
    {
      "bytes": 1548,
      "format": "md",
      "path": "demo/compatibility_report.md",
      "producer_command": "compatibility-report",
      "sha256": "010e133a6e655915b8d20d6495c14bbcf76ad94dab4a384fd459260912312a52",
      "status": "present"
    },
    {
      "bytes": 3472,
      "format": "json",
      "path": "demo/data_dictionary_diff.json",
      "producer_command": "data-dictionary-diff",
      "sha256": "b1c9f49c0cbf3f3d973d83987aec3bf701733c83ecb24ce873802b08dc439768",
      "status": "present"
    },
    {
      "bytes": 2177,
      "format": "md",
      "path": "demo/data_dictionary_diff.md",
      "producer_command": "data-dictionary-diff",
      "sha256": "cfd3eb09350f1e4997b6997964cf340736a4a2f1af5f69bb332f3bff5af4cf69",
      "status": "present"
    },
    {
      "bytes": 9113,
      "format": "json",
      "path": "demo/docs_export.json",
      "producer_command": "docs-export",
      "sha256": "7abe99a8aeda92bf58d9b163d6cabb13e8026d1c59a3cdfac43f0af216c14913",
      "status": "present"
    },
    {
      "bytes": 4784,
      "format": "md",
      "path": "demo/docs_export.md",
      "producer_command": "docs-export",
      "sha256": "bf2d1c2f3377b0598631f1f3584ac452c603585a24aa905d1750620e1156850d",
      "status": "present"
    },
    {
      "bytes": 2250,
      "format": "json",
      "path": "demo/evaluator_scorecard.json",
      "producer_command": "evaluator-scorecard",
      "sha256": "4e534075cd2001322dc8c5536edc4ac2e09bc64f8a0850f6cea613023a751915",
      "status": "present"
    },
    {
      "bytes": 1751,
      "format": "md",
      "path": "demo/evaluator_scorecard.md",
      "producer_command": "evaluator-scorecard",
      "sha256": "8d0d9e4c6069919a8fabb09843f4a6734231f64141aedbe71b56daeadc64ca27",
      "status": "present"
    },
    {
      "bytes": 19080,
      "format": "json",
      "path": "demo/evidence_bundle.json",
      "producer_command": "evidence-bundle",
      "sha256": "c2985ca1793291c85d657569bde2fab7dbe4c1c65404d916bb22a813887d5f5a",
      "status": "present"
    },
    {
      "bytes": 8158,
      "format": "md",
      "path": "demo/evidence_bundle.md",
      "producer_command": "evidence-bundle",
      "sha256": "5c2713cafad3e04911a641bdf91973d856382f46ee462c9819ed039d3c6fc25c",
      "status": "present"
    },
    {
      "bytes": 2945,
      "format": "html",
      "path": "demo/example_pack.html",
      "producer_command": "example-pack",
      "sha256": "8c221a2fe609c985438178454547c532505dfd399dd157ab464bb56f16b286a8",
      "status": "present"
    },
    {
      "bytes": 3795,
      "format": "json",
      "path": "demo/example_pack.json",
      "producer_command": "example-pack",
      "sha256": "935a6dab9ce220cf74a1065b02f22d9b665e563b40ede358609f940c5c6f2c84",
      "status": "present"
    },
    {
      "bytes": 2132,
      "format": "md",
      "path": "demo/example_pack.md",
      "producer_command": "example-pack",
      "sha256": "b06724bf250cfc33fd1f298441a8705436d532677d40df541d0eea2bd7d964f8",
      "status": "present"
    },
    {
      "bytes": 3334,
      "format": "json",
      "path": "demo/exposure_map.json",
      "producer_command": "exposure-map",
      "sha256": "e99f1a3387a9baa54344f2599d7be678cc650dade2abf09bfe2f7dc07c5d10f1",
      "status": "present"
    },
    {
      "bytes": 1722,
      "format": "md",
      "path": "demo/exposure_map.md",
      "producer_command": "exposure-map",
      "sha256": "78bb263d749d469a079b0dbaff374fcc2151e15eb7224f96e0ff17ebe7b9a33e",
      "status": "present"
    },
    {
      "bytes": 985,
      "format": "json",
      "path": "demo/fixture_doctor.json",
      "producer_command": "fixture-doctor",
      "sha256": "56410778254836def7ff35b8ac9a2aaef5d6a37feca1523411852a80d41c0a15",
      "status": "present"
    },
    {
      "bytes": 534,
      "format": "md",
      "path": "demo/fixture_doctor.md",
      "producer_command": "fixture-doctor",
      "sha256": "6c06972b77c0882aa39ee96843a398c1c8a0d5d1b2ed645d634cbbdf77314314",
      "status": "present"
    },
    {
      "bytes": 4685,
      "format": "json",
      "path": "demo/golden_fixtures.json",
      "producer_command": "golden-fixtures",
      "sha256": "99a3213b8530a9a4362b7492d28c3782989c622109386afe5ceea50d551b1349",
      "status": "present"
    },
    {
      "bytes": 1287,
      "format": "md",
      "path": "demo/golden_fixtures.md",
      "producer_command": "golden-fixtures",
      "sha256": "a8d4b690ee52dd7e25eba991bd7effe94e7f4fe4433fab752aa824b19d78c502",
      "status": "present"
    },
    {
      "bytes": 1197,
      "format": "json",
      "path": "demo/history_comparison.json",
      "producer_command": "compare-history",
      "sha256": "999b0f50d04e7fa9d8c8e8ace0e996ea5ecac115b8901bc9f29e221af03dfa05",
      "status": "present"
    },
    {
      "bytes": 635,
      "format": "md",
      "path": "demo/history_comparison.md",
      "producer_command": "compare-history",
      "sha256": "aaa45f9f26551651831ab4b800b170a51b81e68e4cd331ec9e25d6d7a8ec1b8e",
      "status": "present"
    },
    {
      "bytes": 2845,
      "format": "json",
      "path": "demo/input_schema.json",
      "producer_command": "schema-export",
      "sha256": "02f643407959d64c28952613e83c131d3363a3132d4527b1d96c889786a5b7f7",
      "status": "present"
    },
    {
      "bytes": 1997,
      "format": "md",
      "path": "demo/input_schema.md",
      "producer_command": "schema-export",
      "sha256": "421c6402eea9862e8a2938cdc3474a2bb2874b812c062bfb27bf6c715d83ccc8",
      "status": "present"
    },
    {
      "bytes": 3546,
      "format": "json",
      "path": "demo/integration_cookbook.json",
      "producer_command": "integration-cookbook",
      "sha256": "a4c794f009d7bede618c185653c37ae287f8e09024eaf7186bc95fad880bf6ba",
      "status": "present"
    },
    {
      "bytes": 2480,
      "format": "md",
      "path": "demo/integration_cookbook.md",
      "producer_command": "integration-cookbook",
      "sha256": "dc5b28704653220f10ec9e89a58e44ba6a2bead4dbfb1a2f155a53cec18332a5",
      "status": "present"
    },
    {
      "bytes": 3860,
      "format": "html",
      "path": "demo/landing_page.html",
      "producer_command": "landing-page",
      "sha256": "2e0c917e4863319d996d2b99ce65e39de63546e3e6521679d36e0e0c016e52af",
      "status": "present"
    },
    {
      "bytes": 6046,
      "format": "json",
      "path": "demo/landing_page.json",
      "producer_command": "landing-page",
      "sha256": "9ff1501b33a0058f73d0ca081935070750d03fdea3d79e0143ca1cf3dec7bf63",
      "status": "present"
    },
    {
      "bytes": 3222,
      "format": "md",
      "path": "demo/landing_page.md",
      "producer_command": "landing-page",
      "sha256": "680a264ce0740f738038a686f4c861025f553e1352de4b580a5425886ed622af",
      "status": "present"
    },
    {
      "bytes": 2594,
      "format": "json",
      "path": "demo/maintainer_guide.json",
      "producer_command": "maintainer-guide",
      "sha256": "23c3bcd8b3958d2ad7c5605af7a75ac746774e84342b9d2677458e51493acf9f",
      "status": "present"
    },
    {
      "bytes": 2336,
      "format": "md",
      "path": "demo/maintainer_guide.md",
      "producer_command": "maintainer-guide",
      "sha256": "1d9901d4b3a63a35d1393607a2d37440421960b9f65764ff8a6ccbec495f3785",
      "status": "present"
    },
    {
      "bytes": 3508,
      "format": "json",
      "path": "demo/maintainer_handoff.json",
      "producer_command": "maintainer-handoff",
      "sha256": "a5a1daf57bf987d0c8b131529e90b810c144aac49b505686e78941e8776983be",
      "status": "present"
    },
    {
      "bytes": 2429,
      "format": "md",
      "path": "demo/maintainer_handoff.md",
      "producer_command": "maintainer-handoff",
      "sha256": "6bead6e0c9098ec6c701a7106ec681b4009f4557d552e93fd9f111ec9bafc598",
      "status": "present"
    },
    {
      "bytes": 1622,
      "format": "json",
      "path": "demo/maturity_report.json",
      "producer_command": "maturity-report",
      "sha256": "02f3a3edd8df91a34b938589e0da1692f5f136e0c2a68229217ef98ae179f912",
      "status": "present"
    },
    {
      "bytes": 852,
      "format": "md",
      "path": "demo/maturity_report.md",
      "producer_command": "maturity-report",
      "sha256": "622bd663f4fc2576ce0b1f9cc4dc830a5b13ac39b5d88e62b7675d44d6392075",
      "status": "present"
    },
    {
      "bytes": 2593,
      "format": "json",
      "path": "demo/onboarding_checklist.json",
      "producer_command": "onboarding-checklist",
      "sha256": "e3944b057ecfcc8b18de580d0f960e9cf7521b732fd28c38c6b3251bf14fc0a3",
      "status": "present"
    },
    {
      "bytes": 2209,
      "format": "md",
      "path": "demo/onboarding_checklist.md",
      "producer_command": "onboarding-checklist",
      "sha256": "29e572d330eb545e51ef0d6ac993ddd75a6c2838a19db253d310a46884369289",
      "status": "present"
    },
    {
      "bytes": 26766,
      "format": "json",
      "path": "demo/provenance_ledger.json",
      "producer_command": "provenance-ledger",
      "sha256": "16af0d34681e26e45986b44fb279c6595b1c32b5547d1e2fda70703e28445838",
      "status": "present"
    },
    {
      "bytes": 10109,
      "format": "md",
      "path": "demo/provenance_ledger.md",
      "producer_command": "provenance-ledger",
      "sha256": "83cf3b41216bee6579e99228603605c316a3bf1e108771d00ab63e4c0510047a",
      "status": "present"
    },
    {
      "bytes": 2471,
      "format": "json",
      "path": "demo/public_readiness.json",
      "producer_command": "public-readiness",
      "sha256": "d45135eba9e8effbf61378dd00daab485b67320370eed81a56f07ae5b4ee05c8",
      "status": "present"
    },
    {
      "bytes": 1783,
      "format": "md",
      "path": "demo/public_readiness.md",
      "producer_command": "public-readiness",
      "sha256": "2573dcbb3707aee83f3f601bac7b92368f8be0524d4532a094aac5625476a83c",
      "status": "present"
    },
    {
      "bytes": 10899,
      "format": "json",
      "path": "demo/quickstart_check.json",
      "producer_command": "quickstart-check",
      "sha256": "9b100b1f36a95f56589665943a00a043fd8dfee1655ecb3e22b2974c1f278004",
      "status": "present"
    },
    {
      "bytes": 6895,
      "format": "md",
      "path": "demo/quickstart_check.md",
      "producer_command": "quickstart-check",
      "sha256": "101410efb29af7360c9d840e0aa06bb9e331c20f222c095691dc43522589850e",
      "status": "present"
    },
    {
      "bytes": 6230,
      "format": "json",
      "path": "demo/readme_snippet.json",
      "producer_command": "readme-snippet",
      "sha256": "99265ac326496199a30729704231b8c95e4f00475285f224e9c89e9df79979e5",
      "status": "present"
    },
    {
      "bytes": 3503,
      "format": "md",
      "path": "demo/readme_snippet.md",
      "producer_command": "readme-snippet",
      "sha256": "798d4ed518b2c24ee585ba7c52f85994ee6c62062b900121dab6a6417723a25d",
      "status": "present"
    },
    {
      "bytes": 3389,
      "format": "json",
      "path": "demo/regression_summary.json",
      "producer_command": "regression-summary",
      "sha256": "55721620ea052ddced8abb67447cb5d8edf620bbd013826d8e20eba09e6ed0ae",
      "status": "present"
    },
    {
      "bytes": 2651,
      "format": "md",
      "path": "demo/regression_summary.md",
      "producer_command": "regression-summary",
      "sha256": "01303ace7d520486608f48d97e649a5a876459343989cefd9a7b7c8be7140688",
      "status": "present"
    },
    {
      "bytes": 6461,
      "format": "json",
      "path": "demo/release_deck.json",
      "producer_command": "release-deck",
      "sha256": "d2f0a96338bfff82d6aada1233865c552d3514e64e6016f0223e1284f4f8a013",
      "status": "present"
    },
    {
      "bytes": 3307,
      "format": "md",
      "path": "demo/release_deck.md",
      "producer_command": "release-deck",
      "sha256": "8ac8cfe87a1a5041d43291a4afa352cb55be45a3227e372f12685fa1e43f5818",
      "status": "present"
    },
    {
      "bytes": 2820,
      "format": "json",
      "path": "demo/release_faq.json",
      "producer_command": "release-faq",
      "sha256": "b62bd3e5721b08ca3ddcaf361fdc09228ed072836762a8e324f866ac893b2250",
      "status": "present"
    },
    {
      "bytes": 1894,
      "format": "md",
      "path": "demo/release_faq.md",
      "producer_command": "release-faq",
      "sha256": "9fae7126efe177af2a0d1038a41809b37a2426e2c1fe5dfb334b56d98092d1c7",
      "status": "present"
    },
    {
      "bytes": 18568,
      "format": "json",
      "path": "demo/release_manifest.json",
      "producer_command": "release-manifest",
      "sha256": "365a3a8944e17c4a554e794b89210fbac4c34717afd01d319762daf532e51a53",
      "status": "present"
    },
    {
      "bytes": 6844,
      "format": "md",
      "path": "demo/release_manifest.md",
      "producer_command": "release-manifest",
      "sha256": "6fa1ed5f19c6059c30d86f4ad1b47c78ab0dc3af032e583f23119efc45462906",
      "status": "present"
    },
    {
      "bytes": 2124,
      "format": "json",
      "path": "demo/release_notes_draft.json",
      "producer_command": "release-notes-draft",
      "sha256": "f62415c15621be64b897ad02fa115b76cd41850f4dd2e6ee1b509d4c7948bb10",
      "status": "present"
    },
    {
      "bytes": 2068,
      "format": "md",
      "path": "demo/release_notes_draft.md",
      "producer_command": "release-notes-draft",
      "sha256": "824520c2570ec470d84e378431dd8f06d90e7f5f6bfd4410622552495ffb71d6",
      "status": "present"
    },
    {
      "bytes": 10617,
      "format": "json",
      "path": "demo/reproducibility_recipe.json",
      "producer_command": "reproducibility-recipe",
      "sha256": "5031cf7d6615be3b46b733d2bfaf6451414953fa23cd0852b3f486e73c287aa8",
      "status": "present"
    },
    {
      "bytes": 7608,
      "format": "md",
      "path": "demo/reproducibility_recipe.md",
      "producer_command": "reproducibility-recipe",
      "sha256": "e718e5f02c0a34cb028a713db1873b1c50f37dae4dbf6a5c4202b8d5b145b141",
      "status": "present"
    },
    {
      "bytes": 432,
      "format": "json",
      "path": "demo/review_ledger.json",
      "producer_command": "review-ledger",
      "sha256": "d4f558b50d9e8366a7643dbbdd90e60af0132fcea8bafb978819d6322a40be1a",
      "status": "present"
    },
    {
      "bytes": 367,
      "format": "md",
      "path": "demo/review_ledger.md",
      "producer_command": "review-ledger",
      "sha256": "c19af376680eae282b8c653c74d3e59d1b971fa4fb576c8949ae3a5401a60e1f",
      "status": "present"
    },
    {
      "bytes": 8942,
      "format": "json",
      "path": "demo/reviewer_scorecard.json",
      "producer_command": "reviewer-scorecard",
      "sha256": "60034f732a1c423873c95e16cb4a21e71021bc94f924a2cfb2948787055da0a1",
      "status": "present"
    },
    {
      "bytes": 3668,
      "format": "md",
      "path": "demo/reviewer_scorecard.md",
      "producer_command": "reviewer-scorecard",
      "sha256": "87ad3ac2b6a215fa35e68abdc7c3f391bb1fb47ce6e0331792ffacc7e41e8cc9",
      "status": "present"
    },
    {
      "bytes": 2785,
      "format": "html",
      "path": "demo/roadmap_next.html",
      "producer_command": "roadmap-next",
      "sha256": "7143a953adc3e8de43153ca1d923f3ad21c8c4eb2eef1692ad20c3c3e61aeeb5",
      "status": "present"
    },
    {
      "bytes": 2452,
      "format": "json",
      "path": "demo/roadmap_next.json",
      "producer_command": "roadmap-next",
      "sha256": "394394f2afe8618fa19f95e0ff924d562b7286cb1b5d991fa3a477957ee2ef33",
      "status": "present"
    },
    {
      "bytes": 1954,
      "format": "md",
      "path": "demo/roadmap_next.md",
      "producer_command": "roadmap-next",
      "sha256": "0f979db08f83a7ffa2e7e7329cb6b41587beace86d7a5d6f0a29adb738857bf1",
      "status": "present"
    },
    {
      "bytes": 2903,
      "format": "json",
      "path": "demo/scenario_library.json",
      "producer_command": "scenario-library",
      "sha256": "cc502c7edcf25d4d23e798ba6bf3b2d5acd7280ed8d713cc6b26807161381efa",
      "status": "present"
    },
    {
      "bytes": 1936,
      "format": "md",
      "path": "demo/scenario_library.md",
      "producer_command": "scenario-library",
      "sha256": "231589f27b600c113646a0d24265a4d14c31f06ef9cee9f887dbe5f54867f49a",
      "status": "present"
    },
    {
      "bytes": 2398,
      "format": "html",
      "path": "demo/static_dashboard.html",
      "producer_command": "static-dashboard",
      "sha256": "07515c531d20fbfef2a5be85989f46d2d49046fb15ebb9f2462dfa80520d2ef5",
      "status": "present"
    },
    {
      "bytes": 4389,
      "format": "json",
      "path": "demo/thesis_impact_brief.json",
      "producer_command": "thesis-impact-brief",
      "sha256": "941fcf40523e63ae9e336757c24e7bafa030df0eeb723c284196e24a36f8930c",
      "status": "present"
    },
    {
      "bytes": 2240,
      "format": "md",
      "path": "demo/thesis_impact_brief.md",
      "producer_command": "thesis-impact-brief",
      "sha256": "36867e04943f1a4aa6efc8ddf25bc9865952f3e9e23305840ae3432e5c9f5625",
      "status": "present"
    },
    {
      "bytes": 3659,
      "format": "json",
      "path": "demo/thesis_packet.json",
      "producer_command": "build-packet",
      "sha256": "21afd1a6478ca24314acad778cc1a07cd9ba7a0099af0afe54397d876a5d12a9",
      "status": "present"
    },
    {
      "bytes": 1401,
      "format": "md",
      "path": "demo/thesis_packet.md",
      "producer_command": "build-packet",
      "sha256": "03769420c7f8360437e866116870ebd7fc88431cd96a088d215063b503385406",
      "status": "present"
    },
    {
      "bytes": 3174,
      "format": "json",
      "path": "demo/troubleshoot.json",
      "producer_command": "troubleshoot",
      "sha256": "b986a9d03a2293b74f1f8e195256b9cd4ef34619457619c9a6abd6457f0bdaf2",
      "status": "present"
    },
    {
      "bytes": 2357,
      "format": "md",
      "path": "demo/troubleshoot.md",
      "producer_command": "troubleshoot",
      "sha256": "ae74fa8998c303f0312c3997aa31149fad939e3f3397c17448ef8d84da446d5c",
      "status": "present"
    },
    {
      "bytes": 5130,
      "format": "json",
      "path": "demo/trust_report.json",
      "producer_command": "trust-report",
      "sha256": "212ac784fdce584328f4b1d7faff6ae2fb762d1662e0228cc81f1b5101a433fb",
      "status": "present"
    },
    {
      "bytes": 3128,
      "format": "md",
      "path": "demo/trust_report.md",
      "producer_command": "trust-report",
      "sha256": "844f8ac0e34502f3006f4eff43848060df2f273ab0b2042cfade916324b21afb",
      "status": "present"
    },
    {
      "bytes": 3104,
      "format": "html",
      "path": "demo/visual_receipt.html",
      "producer_command": "release artifact",
      "sha256": "ef267e6e134e7fcbb3660d5daa3286186a35d2d1460f6356aa59f1310abe4458",
      "status": "present"
    },
    {
      "bytes": 3350,
      "format": "json",
      "path": "demo/visual_receipt.json",
      "producer_command": "visual-receipt",
      "sha256": "588f2f479e94550ac568f9327da5859b2e2e08260d187e1338dbd9b7fbf1e119",
      "status": "present"
    },
    {
      "bytes": 2519,
      "format": "svg",
      "path": "demo/visual_receipt.svg",
      "producer_command": "release artifact",
      "sha256": "4fafd5e3bf33d7afcc85fe6ae752d883d01b7909aed6fce65e97c217fa869dc4",
      "status": "present"
    },
    {
      "bytes": 0,
      "format": "html",
      "path": "demo/visual_receipt.svg or demo/visual_receipt.html",
      "producer_command": "visual-receipt",
      "sha256": "",
      "status": "missing"
    },
    {
      "bytes": 2971,
      "format": "html",
      "path": "demo/workflow_protocol.html",
      "producer_command": "workflow-protocol",
      "sha256": "8222cb009238155174470af620838d6b36fdf04a6dd0fc7034e6809a2a694430",
      "status": "present"
    },
    {
      "bytes": 3557,
      "format": "json",
      "path": "demo/workflow_protocol.json",
      "producer_command": "workflow-protocol",
      "sha256": "26555f1efd6289b6c1504f7c28641d7098e505cf97da1ba2678cff6911efe569",
      "status": "present"
    },
    {
      "bytes": 2397,
      "format": "md",
      "path": "demo/workflow_protocol.md",
      "producer_command": "workflow-protocol",
      "sha256": "33bcfea129ebdfc7c7f2e7a413be9f60160bb3d14c0f405a951e9978418a9242",
      "status": "present"
    }
  ],
  "boundaries": "Research-only static analysis. Not investment advice. This tool does not fetch live data, connect to brokers, place orders, recommend buys, sells, holds, target allocations, or trades, predict returns, or produce personalized financial advice.",
  "formats": {
    "html": 7,
    "json": 49,
    "md": 48,
    "svg": 1
  },
  "missing_count": 1,
  "present_count": 105,
  "title": "Artifact Index",
  "version": "1.4.0"
}
